flask_authz/__init__.py
flask_authz/casbin_enforcer.py
flask_authz/utils/__init__.py
flask_authz/utils/auth_decoder.py
flask_authz-2.9.0.data/data/README.md
flask_authz-2.9.0.dist-info/licenses/LICENSE
flask_authz-2.9.0.dist-info/METADATA
flask_authz-2.9.0.dist-info/WHEEL
flask_authz-2.9.0.dist-info/top_level.txt
flask_authz-2.9.0.dist-info/RECORD
