Metadata-Version: 2.4
Name: flask-authz
Version: 2.9.0
Summary: An authorization middleware for Flask that supports ACL, RBAC, ABAC, based on Casbin
Home-page: https://github.com/officialpycasbin/flask-authz
Download-URL: https://github.com/officialpycasbin/flask-authz/tarball/v2.9.0
Author: ['Yang Luo', 'Sciencelogic']
Author-email: hsluoyz@gmail.com
License: Apache 2.0
Keywords: flask,pycasbin,casbin,auth,authz,acl,rbac,abac,access control,authorization,permission
Classifier: Programming Language :: Python :: 3.9
Classifier: Programming Language :: Python :: 3.10
Classifier: Programming Language :: Python :: 3.11
Classifier: Programming Language :: Python :: 3.12
Classifier: License :: OSI Approved :: Apache Software License
Classifier: Operating System :: OS Independent
Requires-Python: >=3.5
License-File: LICENSE
Requires-Dist: blinker==1.9.0
Requires-Dist: click==8.2.1
Requires-Dist: colorama==0.4.6
Requires-Dist: flask==3.1.1
Requires-Dist: itsdangerous==2.2.0
Requires-Dist: jinja2==3.1.6
Requires-Dist: markupsafe==3.0.2
Requires-Dist: pycasbin==2.0.0
Requires-Dist: pyjwt==2.10.1
Requires-Dist: simpleeval==1.0.3
Requires-Dist: werkzeug==3.1.3
Dynamic: author
Dynamic: author-email
Dynamic: classifier
Dynamic: description
Dynamic: description-content-type
Dynamic: download-url
Dynamic: home-page
Dynamic: keywords
Dynamic: license
Dynamic: license-file
Dynamic: requires-dist
Dynamic: requires-python
Dynamic: summary
